[
    {
    "eventid":"1",
    "name":"maitree project",
    "pht":"maitre.jpg",
    "desc":"MAITREE Project is a dedicated project on Model Village Development and Environment Conservation."
    },
    {
    "eventid":"2",
    "name":"maitree project2",
    "pht":"maitre.jpg",
    "desc":"MAITREE Project is a dedicated project on Model Village Development and Environment Conservation."
    },
    {
    "eventid":"3",
    "name":"maitree project3",
    "pht":"maitre.jpg",
    "desc":"MAITREE Project is a dedicated project on Model Village Development and Environment Conservation."
    },
    {
    "eventid":"4",
    "name":"maitree project4",
    "pht":"maitre.jpg",
    "desc":"MAITREE Project is a dedicated project on Model Village Development and Environment Conservation."
    },
    {
    "eventid":"5",
    "name":"maitree project5",
    "pht":"maitre.jpg",
    "desc":"MAITREE Project is a dedicated project on Model Village Development and Environment Conservation."
    },
    {
    "eventid":"6",
    "name":"maitree project6",
    "pht":"maitre.jpg",
    "desc":"MAITREE Project is a dedicated project on Model Village Development and Environment Conservation."
    }
]